lilizong_potato2/__init__.py
lilizong_potato2-0.1.0.dist-info/WHEEL
lilizong_potato2-0.1.0.dist-info/entry_points.txt
lilizong_potato2-0.1.0.dist-info/METADATA
lilizong_potato2-0.1.0.dist-info/RECORD
